{
  "source_image": "006_청정하루.jpg",
  "text_elements": {
    "primary_text": "청청하루",
    "secondary_text": null,
    "language": "Korean",
    "font_style": "traditional",
    "typography_notes": "Clear and legible",
    "confidence": 0.9
  },
  "symbol": {
    "description": "Silhouette of a ginseng root with leaves and flower",
    "category": "abstract",
    "meanings": [
      "nature",
      "health",
      "growth"
    ],
    "confidence": 0.85
  },
  "color_palette": {
    "primary": [
      {
        "hex": "#000000",
        "common_name": "black",
        "usage": "foreground"
      }
    ],
    "secondary": [
      {
        "hex": "#FFFFFF",
        "common_name": "white",
        "usage": "background"
      }
    ],
    "contrast_notes": "High contrast between black and white",
    "confidence": 0.95
  },
  "style_tags": [
    "minimal",
    "traditional"
  ],
  "tone_descriptors": [
    "natural",
    "calm"
  ],
  "layout": {
    "orientation": "vertical",
    "aspect_ratio_estimate": "1:1",
    "balance_notes": "Centered and balanced",
    "spacing_notes": "Adequate white space around elements",
    "confidence": 0.9
  },
  "brand_message": {
    "keywords": [
      "nature",
      "health",
      "tradition"
    ],
    "values": [
      "wellness",
      "purity"
    ],
    "audience_hint": "health-conscious consumers",
    "confidence": 0.85
  },
  "detected_channels": [
    "digital",
    "print"
  ],
  "complexity_rating": "low",
  "issues": [],
  "improvement_cues": [],
  "trend_alignment": {
    "tags": [
      "minimal",
      "nature-inspired"
    ],
    "score": 0.8,
    "notes": "Aligns with trends favoring simplicity and natural themes"
  },
  "analysis_timestamp": "2025-11-10T04:25:27.275511Z"
}