{
  "source_image": "001_BOKJA.jpg",
  "text_elements": {
    "primary_text": "BOKJA",
    "secondary_text": "HAPPYCAFE",
    "language": "Latin",
    "font_style": "bold, rounded",
    "typography_notes": "Primary text is bold and playful, secondary text is smaller and more formal.",
    "confidence": 0.95
  },
  "symbol": {
    "description": "Text-based logo with no additional symbols.",
    "category": "lettermark",
    "meanings": [
      "playfulness",
      "joy"
    ],
    "confidence": 0.9
  },
  "color_palette": {
    "primary": [
      {
        "hex": "#2F4F4F",
        "common_name": "dark green",
        "usage": "foreground"
      }
    ],
    "secondary": [],
    "contrast_notes": "Good contrast between text and background.",
    "confidence": 0.9
  },
  "style_tags": [
    "modern",
    "minimal"
  ],
  "tone_descriptors": [
    "friendly",
    "inviting"
  ],
  "layout": {
    "orientation": "vertical",
    "aspect_ratio_estimate": "1:1",
    "balance_notes": "Centered alignment with balanced text weight.",
    "spacing_notes": "Adequate white space around text.",
    "confidence": 0.9
  },
  "brand_message": {
    "keywords": [
      "cafe",
      "happiness",
      "community"
    ],
    "values": [
      "joy",
      "togetherness"
    ],
    "audience_hint": "young adults, families",
    "confidence": 0.85
  },
  "detected_channels": [
    "digital",
    "print"
  ],
  "complexity_rating": "low",
  "issues": [],
  "improvement_cues": [
    {
      "focus": "color",
      "suggestion": "Consider adding a secondary color for more depth.",
      "priority": "medium"
    }
  ],
  "trend_alignment": {
    "tags": [
      "modern",
      "playful"
    ],
    "score": 0.8,
    "notes": "Aligns well with current trends in minimalistic and playful branding."
  },
  "analysis_timestamp": "2025-11-10T02:42:14.337330Z"
}