{
  "source_image": "040_HUZEN.jpg",
  "text_elements": {
    "primary_text": "HUZEN",
    "secondary_text": "ENGINEERING & CONSTRUCTION",
    "language": "Latin",
    "font_style": "Bold, Sans-serif",
    "typography_notes": "Clear and legible",
    "confidence": 0.95
  },
  "symbol": {
    "description": "3D cube with stylized 'H'",
    "category": "lettermark",
    "meanings": [
      "strength",
      "stability"
    ],
    "confidence": 0.9
  },
  "color_palette": {
    "primary": [
      {
        "hex": "#D32F2F",
        "common_name": "red",
        "usage": "foreground"
      }
    ],
    "secondary": [
      {
        "hex": "#F57C00",
        "common_name": "orange",
        "usage": "accent"
      }
    ],
    "contrast_notes": "Good contrast between text and background",
    "confidence": 0.9
  },
  "style_tags": [
    "modern",
    "bold"
  ],
  "tone_descriptors": [
    "professional",
    "strong"
  ],
  "layout": {
    "orientation": "horizontal",
    "aspect_ratio_estimate": "4:1",
    "balance_notes": "Well-balanced with equal weight on text and symbol",
    "spacing_notes": "Adequate spacing between elements",
    "confidence": 0.9
  },
  "brand_message": {
    "keywords": [
      "engineering",
      "construction",
      "innovation"
    ],
    "values": [
      "reliability",
      "precision"
    ],
    "audience_hint": "industry professionals",
    "confidence": 0.85
  },
  "detected_channels": [
    "digital",
    "print"
  ],
  "complexity_rating": "medium",
  "issues": [],
  "improvement_cues": [
    {
      "focus": "color",
      "suggestion": "Consider adding a neutral color for balance",
      "priority": "low"
    }
  ],
  "trend_alignment": {
    "tags": [
      "modern",
      "geometric"
    ],
    "score": 0.8,
    "notes": "Aligns with current trends in bold and geometric designs"
  },
  "analysis_timestamp": "2025-11-10T05:18:41.259940Z"
}