{
  "source_image": "page1_19.jpg",
  "text_elements": {
    "primary_text": "O.rang",
    "secondary_text": null,
    "language": "Latin",
    "font_style": "Serif",
    "typography_notes": "Readable with a classic touch",
    "confidence": 0.95
  },
  "symbol": {
    "description": "Interlocking letters O and R within an oval",
    "category": "lettermark",
    "meanings": [
      "initials",
      "elegance"
    ],
    "confidence": 0.9
  },
  "color_palette": {
    "primary": [
      {
        "hex": "#004225",
        "common_name": "dark green",
        "usage": "foreground"
      }
    ],
    "secondary": [],
    "contrast_notes": "Good contrast on light background",
    "confidence": 0.9
  },
  "style_tags": [
    "classic",
    "elegant"
  ],
  "tone_descriptors": [
    "sophisticated",
    "professional"
  ],
  "layout": {
    "orientation": "vertical",
    "aspect_ratio_estimate": "3:4",
    "balance_notes": "Well-balanced with central alignment",
    "spacing_notes": "Adequate white space around elements",
    "confidence": 0.9
  },
  "brand_message": {
    "keywords": [
      "elegance",
      "initials"
    ],
    "values": [
      "quality",
      "tradition"
    ],
    "audience_hint": "professional clientele",
    "confidence": 0.85
  },
  "detected_channels": [
    "digital",
    "print"
  ],
  "complexity_rating": "low",
  "issues": [],
  "improvement_cues": [
    {
      "focus": "color",
      "suggestion": "Consider adding a secondary color for depth",
      "priority": "medium"
    }
  ],
  "trend_alignment": {
    "tags": [
      "classic"
    ],
    "score": 0.7,
    "notes": "Aligns with timeless design trends"
  },
  "analysis_timestamp": "2025-11-10T05:42:23.823494Z"
}